{
  "origin": [
    "#[#setPronouns#][#setOccupation#]stanza#"
  ], 
  "seven": [
    "two", 
    "three", 
    "four", 
    "five", 
    "six", 
    "seven", 
    "eight", 
    "nine", 
    "ten", 
    "eleven", 
    "twelve"
  ], 
  "atrociously": [
    "aggressively", 
    "assertively", 
    "decrepitly", 
    "determinedly", 
    "entirely", 
    "essentially", 
    "exultantly", 
    "fallaciously", 
    "ferociously", 
    "impassively", 
    "impulsively", 
    "insistently", 
    "offensively", 
    "prodigiously", 
    "progressively", 
    "respectfully", 
    "unpleasantly"
  ], 
  "watermelon": [
    "apple", 
    "apricot", 
    "avocado", 
    "banana", 
    "bell pepper", 
    "bilberry", 
    "blackberry", 
    "blackcurrant", 
    "blood orange", 
    "blueberry", 
    "boysenberry", 
    "breadfruit", 
    "canary melon", 
    "cantaloupe", 
    "cherimoya", 
    "cherry", 
    "chili pepper", 
    "clementine", 
    "cloudberry", 
    "coconut", 
    "cranberry", 
    "cucumber", 
    "currant", 
    "damson", 
    "date", 
    "dragonfruit", 
    "durian", 
    "eggplant", 
    "elderberry", 
    "feijoa", 
    "fig", 
    "goji berry", 
    "gooseberry", 
    "grape", 
    "grapefruit", 
    "guava", 
    "honeydew", 
    "huckleberry", 
    "jackfruit", 
    "jambul", 
    "jujube", 
    "kiwi fruit", 
    "kumquat", 
    "lemon", 
    "lime", 
    "loquat", 
    "lychee", 
    "mandarine", 
    "mango", 
    "mulberry", 
    "nectarine", 
    "nut", 
    "olive", 
    "orange", 
    "pamelo", 
    "papaya", 
    "passionfruit", 
    "peach", 
    "pear", 
    "persimmon", 
    "physalis", 
    "pineapple", 
    "plum", 
    "pomegranate", 
    "pomelo", 
    "purple mangosteen", 
    "quince", 
    "raisin", 
    "rambutan", 
    "raspberry", 
    "redcurrant", 
    "rock melon", 
    "salal berry", 
    "satsuma", 
    "star fruit", 
    "strawberry", 
    "tamarillo", 
    "tangerine", 
    "ugli fruit", 
    "watermelon"
  ], 
  "setOccupation": [
    "[actor:accountant][acts:accounts]", 
    "[actor:actor][acts:acts]", 
    "[actor:adjudicator][acts:adjudicates]", 
    "[actor:animator][acts:animates]", 
    "[actor:arbitrator][acts:arbitrates]", 
    "[actor:attendant][acts:attends]", 
    "[actor:auditor][acts:audits]", 
    "[actor:baker][acts:bakes]", 
    "[actor:blaster][acts:blasts]", 
    "[actor:butcher][acts:bumbles]", 
    "[actor:buyer][acts:buys]", 
    "[actor:caster][acts:casts]", 
    "[actor:checker][acts:checks]", 
    "[actor:choreographer][acts:choreographs]", 
    "[actor:cleaner][acts:cleanses]", 
    "[actor:composer][acts:composes]", 
    "[actor:conciliator][acts:conciliates]", 
    "[actor:correspondent][acts:corresponds]", 
    "[actor:counselor][acts:counsels]", 
    "[actor:cutter][acts:cuts]", 
    "[actor:dancer][acts:dances]", 
    "[actor:demonstrator][acts:demonstrates]", 
    "[actor:designer][acts:designs]", 
    "[actor:director][acts:directs]", 
    "[actor:dispatcher][acts:dispatches]", 
    "[actor:drafter][acts:drafts]", 
    "[actor:editor][acts:edits]", 
    "[actor:embalmer][acts:embalms]", 
    "[actor:engraver][acts:engraves]", 
    "[actor:etcher][acts:etches]", 
    "[actor:fabricator][acts:fabricates]", 
    "[actor:faller][acts:falls]", 
    "[actor:farmer][acts:farms]", 
    "[actor:fisher][acts:fishes]", 
    "[actor:glazier][acts:glazes]", 
    "[actor:hunter][acts:hunts]", 
    "[actor:illustrator][acts:illustrates]", 
    "[actor:inspector][acts:inspects]", 
    "[actor:instructor][acts:instructs]", 
    "[actor:internist][acts:interns]", 
    "[actor:interpreter][acts:interprets]", 
    "[actor:interviewer][acts:interviews]", 
    "[actor:investigator][acts:investigates]", 
    "[actor:jailer][acts:jails]", 
    "[actor:jeweler][acts:jewels]", 
    "[actor:legislator][acts:legislates]", 
    "[actor:machinist][acts:machines]", 
    "[actor:manicurist][acts:manicures]", 
    "[actor:measurer][acts:measures]", 
    "[actor:mediator][acts:mediates]", 
    "[actor:paperhanger][acts:papers]", 
    "[actor:photographer][acts:photographs]", 
    "[actor:plasterer][acts:plasters]", 
    "[actor:producer][acts:produces]", 
    "[actor:proofreader][acts:proofreads]", 
    "[actor:rancher][acts:ranches]", 
    "[actor:referee][acts:refers]", 
    "[actor:reporter][acts:reports]", 
    "[actor:rigger][acts:rigs]", 
    "[actor:roofer][acts:roofs]", 
    "[actor:sailor][acts:sails]", 
    "[actor:sampler][acts:samples]", 
    "[actor:sculptor][acts:sculptures]", 
    "[actor:shaper][acts:shapes]", 
    "[actor:singer][acts:sings]", 
    "[actor:slaughterer][acts:slaughters]", 
    "[actor:solderer][acts:solders]", 
    "[actor:sorter][acts:sorts]", 
    "[actor:surveyor][acts:surveys]", 
    "[actor:teacher][acts:teaches]", 
    "[actor:teller][acts:tells]", 
    "[actor:tester][acts:tests]", 
    "[actor:translator][acts:translates]", 
    "[actor:trapper][acts:traps]", 
    "[actor:trimmer][acts:trims]", 
    "[actor:tuner][acts:tunes]", 
    "[actor:typist][acts:types]", 
    "[actor:upholsterer][acts:upholsters]", 
    "[actor:veterinarian][acts:vets]", 
    "[actor:waiter][acts:waits]", 
    "[actor:weigher][acts:weighs]", 
    "[actor:welder][acts:welds]", 
    "[actor:writer][acts:writes]"
  ], 
  "superstar": [
    "ace", 
    "adept", 
    "champion", 
    "sensation", 
    "maven", 
    "mavin", 
    "virtuoso", 
    "genius", 
    "hotshot", 
    "star", 
    "superstar", 
    "whiz", 
    "whizz", 
    "wizard", 
    "wiz"
  ], 
  "setPronouns": [
    "[he:he][him:him][hes:he's]", 
    "[he:she][him:her][hes:she's]", 
    "[he:it][him:it][hes:it's]"
  ], 
  "arm": [
    "ankle", 
    "arm", 
    "back", 
    "belly", 
    "bottom", 
    "breast", 
    "buttocks", 
    "calf", 
    "cheek", 
    "chin", 
    "ear", 
    "elbow", 
    "eye", 
    "eyebrow", 
    "eyelash", 
    "finger", 
    "fist", 
    "foot", 
    "forearm", 
    "forehead", 
    "hair", 
    "hand", 
    "head", 
    "hip", 
    "knee", 
    "leg", 
    "lip", 
    "lower leg", 
    "mouth", 
    "neck", 
    "nose", 
    "nostril", 
    "shoulder", 
    "thigh", 
    "thumb", 
    "toe", 
    "tongue", 
    "tooth", 
    "upper arm", 
    "waist", 
    "wrist"
  ], 
  "stanza": [
    "#he# can break my #arm# in #seven# places\n#he# can eat a whole #watermelon#", 
    "#he# may not be an #actor#\n#he# #acts# #atrociously#", 
    "#he# may not be an #actor#\n#he# #acts# #atrociously#"
  ]
}